[
  { "inputs": [], "stateMutability": "nonpayable", "type": "constructor" },
  {
    "anonymous": false,
    "inputs": [
      {
        "indexed": false,
        "internalType": "address",
        "name": "previousAdmin",
        "type": "address"
      },
      {
        "indexed": false,
        "internalType": "address",
        "name": "newAdmin",
        "type": "address"
      }
    ],
    "name": "AdminChanged",
    "type": "event"
  },
  {
    "anonymous": false,
    "inputs": [
      {
        "indexed": true,
        "internalType": "address",
        "name": "beacon",
        "type": "address"
      }
    ],
    "name": "BeaconUpgraded",
    "type": "event"
  },
  {
    "anonymous": false,
    "inputs": [
      {
        "indexed": true,
        "internalType": "address",
        "name": "index",
        "type": "address"
      },
      {
        "indexed": true,
        "internalType": "address",
        "name": "recipient",
        "type": "address"
      },
      {
        "indexed": false,
        "internalType": "uint256",
        "name": "share",
        "type": "uint256"
      }
    ],
    "name": "Burn",
    "type": "event"
  },
  {
    "anonymous": false,
    "inputs": [
      {
        "indexed": false,
        "internalType": "uint8",
        "name": "version",
        "type": "uint8"
      }
    ],
    "name": "Initialized",
    "type": "event"
  },
  {
    "anonymous": false,
    "inputs": [
      {
        "indexed": true,
        "internalType": "address",
        "name": "index",
        "type": "address"
      },
      {
        "indexed": true,
        "internalType": "address",
        "name": "recipient",
        "type": "address"
      },
      {
        "indexed": false,
        "internalType": "uint256",
        "name": "share",
        "type": "uint256"
      }
    ],
    "name": "Mint",
    "type": "event"
  },
  {
    "anonymous": false,
    "inputs": [
      {
        "indexed": true,
        "internalType": "address",
        "name": "account",
        "type": "address"
      },
      {
        "indexed": true,
        "internalType": "address",
        "name": "index",
        "type": "address"
      },
      {
        "indexed": false,
        "internalType": "uint256",
        "name": "AUMScaledPerSecondsRate",
        "type": "uint256"
      }
    ],
    "name": "SetAUMScaledPerSecondsRate",
    "type": "event"
  },
  {
    "anonymous": false,
    "inputs": [
      {
        "indexed": true,
        "internalType": "address",
        "name": "account",
        "type": "address"
      },
      {
        "indexed": true,
        "internalType": "address",
        "name": "index",
        "type": "address"
      },
      {
        "indexed": false,
        "internalType": "uint16",
        "name": "burningFeeInPB",
        "type": "uint16"
      }
    ],
    "name": "SetBurningFeeInBP",
    "type": "event"
  },
  {
    "anonymous": false,
    "inputs": [
      {
        "indexed": true,
        "internalType": "address",
        "name": "account",
        "type": "address"
      },
      {
        "indexed": true,
        "internalType": "address",
        "name": "index",
        "type": "address"
      },
      {
        "indexed": false,
        "internalType": "uint16",
        "name": "mintingFeeInBP",
        "type": "uint16"
      }
    ],
    "name": "SetMintingFeeInBP",
    "type": "event"
  },
  {
    "anonymous": false,
    "inputs": [
      {
        "indexed": true,
        "internalType": "address",
        "name": "implementation",
        "type": "address"
      }
    ],
    "name": "Upgraded",
    "type": "event"
  },
  {
    "anonymous": false,
    "inputs": [
      {
        "indexed": true,
        "internalType": "address",
        "name": "index",
        "type": "address"
      },
      {
        "indexed": true,
        "internalType": "address",
        "name": "recipient",
        "type": "address"
      },
      {
        "indexed": false,
        "internalType": "uint256",
        "name": "amount",
        "type": "uint256"
      }
    ],
    "name": "Withdraw",
    "type": "event"
  },
  {
    "inputs": [{ "internalType": "address", "name": "", "type": "address" }],
    "name": "AUMScaledPerSecondsRateOf",
    "outputs": [{ "internalType": "uint256", "name": "", "type": "uint256" }],
    "stateMutability": "view",
    "type": "function"
  },
  {
    "inputs": [],
    "name": "MAX_AUM_FEE",
    "outputs": [{ "internalType": "uint256", "name": "", "type": "uint256" }],
    "stateMutability": "view",
    "type": "function"
  },
  {
    "inputs": [],
    "name": "MAX_FEE_IN_BP",
    "outputs": [{ "internalType": "uint256", "name": "", "type": "uint256" }],
    "stateMutability": "view",
    "type": "function"
  },
  {
    "inputs": [
      { "internalType": "address", "name": "_index", "type": "address" },
      {
        "components": [
          { "internalType": "address", "name": "recipient", "type": "address" },
          { "internalType": "uint256", "name": "share", "type": "uint256" }
        ],
        "internalType": "struct IFeePool.MintBurnInfo",
        "name": "_burnInfo",
        "type": "tuple"
      }
    ],
    "name": "burn",
    "outputs": [],
    "stateMutability": "nonpayable",
    "type": "function"
  },
  {
    "inputs": [
      { "internalType": "address", "name": "_index", "type": "address" },
      {
        "components": [
          { "internalType": "address", "name": "recipient", "type": "address" },
          { "internalType": "uint256", "name": "share", "type": "uint256" }
        ],
        "internalType": "struct IFeePool.MintBurnInfo[]",
        "name": "_burnInfo",
        "type": "tuple[]"
      }
    ],
    "name": "burnMultiple",
    "outputs": [],
    "stateMutability": "nonpayable",
    "type": "function"
  },
  {
    "inputs": [{ "internalType": "address", "name": "", "type": "address" }],
    "name": "burningFeeInBPOf",
    "outputs": [{ "internalType": "uint16", "name": "", "type": "uint16" }],
    "stateMutability": "view",
    "type": "function"
  },
  {
    "inputs": [
      { "internalType": "address", "name": "_registry", "type": "address" }
    ],
    "name": "initialize",
    "outputs": [],
    "stateMutability": "nonpayable",
    "type": "function"
  },
  {
    "inputs": [
      { "internalType": "address", "name": "_index", "type": "address" },
      { "internalType": "uint16", "name": "_mintingFeeInBP", "type": "uint16" },
      { "internalType": "uint16", "name": "_burningFeeInBP", "type": "uint16" },
      {
        "internalType": "uint256",
        "name": "_AUMScaledPerSecondsRate",
        "type": "uint256"
      },
      {
        "components": [
          { "internalType": "address", "name": "recipient", "type": "address" },
          { "internalType": "uint256", "name": "share", "type": "uint256" }
        ],
        "internalType": "struct IFeePool.MintBurnInfo[]",
        "name": "_mintInfo",
        "type": "tuple[]"
      }
    ],
    "name": "initializeIndex",
    "outputs": [],
    "stateMutability": "nonpayable",
    "type": "function"
  },
  {
    "inputs": [
      { "internalType": "address", "name": "_index", "type": "address" },
      {
        "components": [
          { "internalType": "address", "name": "recipient", "type": "address" },
          { "internalType": "uint256", "name": "share", "type": "uint256" }
        ],
        "internalType": "struct IFeePool.MintBurnInfo",
        "name": "_mintInfo",
        "type": "tuple"
      }
    ],
    "name": "mint",
    "outputs": [],
    "stateMutability": "nonpayable",
    "type": "function"
  },
  {
    "inputs": [
      { "internalType": "address", "name": "_index", "type": "address" },
      {
        "components": [
          { "internalType": "address", "name": "recipient", "type": "address" },
          { "internalType": "uint256", "name": "share", "type": "uint256" }
        ],
        "internalType": "struct IFeePool.MintBurnInfo[]",
        "name": "_mintInfo",
        "type": "tuple[]"
      }
    ],
    "name": "mintMultiple",
    "outputs": [],
    "stateMutability": "nonpayable",
    "type": "function"
  },
  {
    "inputs": [{ "internalType": "address", "name": "", "type": "address" }],
    "name": "mintingFeeInBPOf",
    "outputs": [{ "internalType": "uint16", "name": "", "type": "uint16" }],
    "stateMutability": "view",
    "type": "function"
  },
  {
    "inputs": [],
    "name": "proxiableUUID",
    "outputs": [{ "internalType": "bytes32", "name": "", "type": "bytes32" }],
    "stateMutability": "view",
    "type": "function"
  },
  {
    "inputs": [
      { "internalType": "address", "name": "_index", "type": "address" },
      {
        "internalType": "uint256",
        "name": "_AUMScaledPerSecondsRate",
        "type": "uint256"
      }
    ],
    "name": "setAUMScaledPerSecondsRate",
    "outputs": [],
    "stateMutability": "nonpayable",
    "type": "function"
  },
  {
    "inputs": [
      { "internalType": "address", "name": "_index", "type": "address" },
      { "internalType": "uint16", "name": "_burningFeeInBP", "type": "uint16" }
    ],
    "name": "setBurningFeeInBP",
    "outputs": [],
    "stateMutability": "nonpayable",
    "type": "function"
  },
  {
    "inputs": [
      { "internalType": "address", "name": "_index", "type": "address" },
      { "internalType": "uint16", "name": "_mintingFeeInBP", "type": "uint16" }
    ],
    "name": "setMintingFeeInBP",
    "outputs": [],
    "stateMutability": "nonpayable",
    "type": "function"
  },
  {
    "inputs": [
      { "internalType": "address", "name": "", "type": "address" },
      { "internalType": "address", "name": "", "type": "address" }
    ],
    "name": "shareOf",
    "outputs": [{ "internalType": "uint256", "name": "", "type": "uint256" }],
    "stateMutability": "view",
    "type": "function"
  },
  {
    "inputs": [
      { "internalType": "bytes4", "name": "_interfaceId", "type": "bytes4" }
    ],
    "name": "supportsInterface",
    "outputs": [{ "internalType": "bool", "name": "", "type": "bool" }],
    "stateMutability": "view",
    "type": "function"
  },
  {
    "inputs": [{ "internalType": "address", "name": "", "type": "address" }],
    "name": "totalSharesOf",
    "outputs": [{ "internalType": "uint256", "name": "", "type": "uint256" }],
    "stateMutability": "view",
    "type": "function"
  },
  {
    "inputs": [
      {
        "internalType": "address",
        "name": "newImplementation",
        "type": "address"
      }
    ],
    "name": "upgradeTo",
    "outputs": [],
    "stateMutability": "nonpayable",
    "type": "function"
  },
  {
    "inputs": [
      {
        "internalType": "address",
        "name": "newImplementation",
        "type": "address"
      },
      { "internalType": "bytes", "name": "data", "type": "bytes" }
    ],
    "name": "upgradeToAndCall",
    "outputs": [],
    "stateMutability": "payable",
    "type": "function"
  },
  {
    "inputs": [
      { "internalType": "address", "name": "_index", "type": "address" }
    ],
    "name": "withdraw",
    "outputs": [],
    "stateMutability": "nonpayable",
    "type": "function"
  },
  {
    "inputs": [
      { "internalType": "address", "name": "_index", "type": "address" },
      { "internalType": "address", "name": "_recipient", "type": "address" }
    ],
    "name": "withdrawPlatformFeeOf",
    "outputs": [],
    "stateMutability": "nonpayable",
    "type": "function"
  },
  {
    "inputs": [
      { "internalType": "address", "name": "_index", "type": "address" },
      { "internalType": "address", "name": "_account", "type": "address" }
    ],
    "name": "withdrawableAmountOf",
    "outputs": [{ "internalType": "uint256", "name": "", "type": "uint256" }],
    "stateMutability": "view",
    "type": "function"
  }
]
